cheap_modbus_rtu/__init__.py
cheap_modbus_rtu/cheap_modbus_io.py
cheap_modbus_rtu/crc16_modbus.py
cheap_modbus_rtu/modbus_rtu_master.py
cheap_modbus_rtu-0.1.1.dist-info/LICENSE
cheap_modbus_rtu-0.1.1.dist-info/METADATA
cheap_modbus_rtu-0.1.1.dist-info/WHEEL
cheap_modbus_rtu-0.1.1.dist-info/top_level.txt
cheap_modbus_rtu-0.1.1.dist-info/RECORD
