Metadata-Version: 2.1
Name: cheap-modbus-rtu
Version: 0.1.1
Summary: Lightweight control of cheap Modbus RTU components using Python
Author-email: Ulrich Lukas <ul-gh@datenparkplatz.de>
License: GNU GENERAL PUBLIC LICENSE
Project-URL: Homepage, https://github.com/ul-gh/cheap_modbus_rtu
Classifier: Programming Language :: Python :: 3
Requires-Python: >=3.9
License-File: LICENSE
Requires-Dist: pyserial
